synphony_cli/__init__.py
synphony_cli/main.py
synphony_cli-0.1.1.dist-info/METADATA
synphony_cli-0.1.1.dist-info/WHEEL
synphony_cli-0.1.1.dist-info/entry_points.txt
synphony_cli-0.1.1.dist-info/top_level.txt
synphony_cli-0.1.1.dist-info/RECORD
