Metadata-Version: 2.4
Name: synphony-cli
Version: 0.1.1
Summary: Command line interface for Synphony robotics data platform
Author-email: Synphony <dev@synphony.co>
License: MIT
Project-URL: Homepage, https://synphony.co
Project-URL: Documentation, https://docs.synphony.co
Project-URL: Repository, https://github.com/synphonyco/synphony-cli
Keywords: robotics,data,video,augmentation,cli
Classifier: Development Status :: 4 - Beta
Classifier: Environment :: Console
Classifier: Intended Audience :: Developers
Classifier: Intended Audience :: Science/Research
Classifier: License :: OSI Approved :: MIT License
Classifier: Operating System :: OS Independent
Classifier: Programming Language :: Python :: 3
Classifier: Programming Language :: Python :: 3.8
Classifier: Programming Language :: Python :: 3.9
Classifier: Programming Language :: Python :: 3.10
Classifier: Programming Language :: Python :: 3.11
Classifier: Programming Language :: Python :: 3.12
Classifier: Topic :: Scientific/Engineering :: Artificial Intelligence
Requires-Python: >=3.8
Requires-Dist: click>=8.0.0
Requires-Dist: requests>=2.25.0
